torch_ema/__init__.py
torch_ema/_version.py
torch_ema/ema.py
torch_ema-0.3.dist-info/LICENSE
torch_ema-0.3.dist-info/METADATA
torch_ema-0.3.dist-info/WHEEL
torch_ema-0.3.dist-info/top_level.txt
torch_ema-0.3.dist-info/RECORD
